{"frameRate":24,"name":"girlAnimation","version":"5.5","compatibleVersion":"5.5","armature":[{"type":"Armature","frameRate":24,"name":"Armature","aabb":{"x":-119.5,"y":-312,"width":270,"height":444.58},"bone":[{"name":"root"},{"length":84,"name":"right arm","parent":"root","transform":{"x":37,"y":-39.5,"skX":63.7413,"skY":63.7413}},{"length":78,"name":"left arm","parent":"root","transform":{"x":-28,"y":-38,"skX":108.6669,"skY":108.6669}},{"length":111,"name":"body","parent":"root","transform":{"x":-1,"y":-44,"skX":85.8777,"skY":85.8777}},{"length":209,"name":"head","parent":"root","transform":{"x":-2,"y":-54,"skX":-88.6295,"skY":-88.6295}},{"length":56,"name":"rigth leg","parent":"root","transform":{"x":26.79,"y":51.88,"skX":81.8699,"skY":81.8699}},{"length":53,"name":"left leg","parent":"root","transform":{"x":-15,"y":55,"skX":91.0809,"skY":91.0809}}],"slot":[{"name":"left leg","parent":"left leg"},{"name":"rigth leg","parent":"rigth leg"},{"name":"left arm","parent":"left arm"},{"name":"body","parent":"body"},{"name":"head","parent":"head"},{"name":"right arm","parent":"right arm"},{"name":"left eye","parent":"root"},{"name":"riht eye","parent":"root"}],"skin":[{"slot":[{"name":"body","display":[{"type":"mesh","name":"body","width":140,"height":136,"vertices":[-65.5,-58.5,74.5,-58.5,-65.5,77.5,74.5,77.5],"uvs":[0,0,1,0,0,1,1,1],"triangles":[1,0,3,0,2,3],"weights":[1,3,1,1,3,1,1,3,1,1,3,1],"slotPose":[1,0,0,1,0,0],"bonePose":[3,0.071886,0.997413,-0.997413,0.071886,-1,-44],"edges":[0,1,1,3,3,2,2,0],"userEdges":[]}]},{"name":"head","display":[{"type":"mesh","name":"head","width":270,"height":269,"vertices":[-119.5,-312,150.5,-312,-119.5,-43,150.5,-43],"uvs":[0,0,1,0,0,1,1,1],"triangles":[1,0,3,0,2,3],"weights":[1,4,1,1,4,1,1,4,1,1,4,1],"slotPose":[1,0,0,1,0,0],"bonePose":[4,0.023917,-0.999714,0.999714,0.023917,-2,-54],"edges":[0,1,1,3,3,2,2,0],"userEdges":[]}]},{"name":"right arm","display":[{"type":"mesh","name":"right arm","width":90,"height":124,"vertices":[12.5,-57.45,102.5,-57.45,12.5,66.55,102.5,66.55],"uvs":[0,0,1,0,0,1,1,1],"triangles":[1,0,3,0,2,3],"weights":[1,1,1,1,1,1,1,1,1,1,1,1],"slotPose":[1,0,0,1,0,0],"bonePose":[1,0.442424,0.896806,-0.896806,0.442424,38,-37],"edges":[0,1,1,3,3,2,2,0],"userEdges":[]}]},{"name":"left eye","display":[{"type":"mesh","name":"left eye","width":56,"height":57,"vertices":[-77.5,-146,-21.5,-146,-77.5,-89,-21.5,-92.2],"uvs":[0,0,1,0,0,1,0.99998,0.94737],"triangles":[1,0,3,0,2,3],"edges":[0,1,1,3,3,2,2,0],"userEdges":[]}]},{"name":"riht eye","display":[{"name":"riht eye","transform":{"x":22.5,"y":-115.5}}]},{"name":"left leg","display":[{"type":"mesh","name":"left leg","width":84,"height":90,"vertices":[-50,38.5,34,38.5,-50,128.5,34,128.5],"uvs":[0,0,1,0,0,1,1,1],"triangles":[1,0,3,0,2,3],"weights":[1,6,1,1,6,1,1,6,1,1,6,1],"slotPose":[1,0,0,1,0,0],"bonePose":[6,-0.018865,0.999822,-0.999822,-0.018865,-15,55],"edges":[0,1,1,3,3,2,2,0],"userEdges":[]}]},{"name":"rigth leg","display":[{"type":"mesh","name":"rigth leg","width":99,"height":90,"vertices":[-24,43.7,75,43.7,-24,133.7,75,133.7],"uvs":[0,0,1,0,0,1,1,1],"triangles":[1,0,3,0,2,3],"weights":[1,5,1,1,5,1,1,5,1,1,5,1],"slotPose":[1,0,0,1,0,0],"bonePose":[5,0.141421,0.989949,-0.989949,0.141421,28,53],"edges":[0,1,1,3,3,2,2,0],"userEdges":[]}]},{"name":"left arm","display":[{"type":"mesh","name":"left arm","width":75,"height":125,"vertices":[-86,-71,-11,-71,-86,54,-11,54],"uvs":[0,0,1,0,0,1,1,1],"triangles":[1,0,3,0,2,3],"weights":[1,2,1,1,2,1,1,2,1,1,2,1],"slotPose":[1,0,0,1,0,0],"bonePose":[2,-0.320066,0.947395,-0.947395,-0.320066,-28,-38],"edges":[0,1,1,3,3,2,2,0],"userEdges":[]}]}]}],"animation":[{"duration":24,"playTimes":0,"name":"walking","bone":[{"name":"right arm","rotateFrame":[{"duration":6,"tweenEasing":0},{"duration":6,"tweenEasing":0,"rotate":15.77},{"duration":6,"tweenEasing":0,"rotate":4.66},{"duration":6,"tweenEasing":0,"rotate":-6.58},{"duration":0,"rotate":0.6}]},{"name":"left arm","rotateFrame":[{"duration":6,"tweenEasing":0},{"duration":6,"tweenEasing":0,"rotate":-26.57},{"duration":6,"tweenEasing":0,"rotate":2.48},{"duration":6,"tweenEasing":0,"rotate":7.31},{"duration":0,"rotate":-2.01}]},{"name":"body","rotateFrame":[{"duration":12,"tweenEasing":0},{"duration":12,"tweenEasing":0,"rotate":1.27},{"duration":0,"rotate":-0.99}]},{"name":"head","rotateFrame":[{"duration":12,"tweenEasing":0},{"duration":12,"tweenEasing":0,"rotate":-1.27},{"duration":0,"rotate":0.16}]},{"name":"rigth leg","rotateFrame":[{"duration":6,"tweenEasing":0},{"duration":6,"tweenEasing":0,"rotate":-12.7},{"duration":6,"tweenEasing":0,"rotate":19.15},{"duration":6,"tweenEasing":0,"rotate":24.2},{"duration":0,"rotate":0.32}]},{"name":"left leg","rotateFrame":[{"duration":6,"tweenEasing":0},{"duration":6,"tweenEasing":0,"rotate":17.75},{"duration":6,"tweenEasing":0,"rotate":5.92},{"duration":6,"tweenEasing":0,"rotate":-28.08},{"duration":0,"rotate":1.4}]}]}],"defaultActions":[{"gotoAndPlay":"walking"}]}]}